[
  {
    "Name": "Copper Sword",
    "Description": "Made of copper, very weak.",
    "Icon": "copper_sword",
    "Type": "WEAPON_1H",
    "Price": 0,
    "Requirements": [
      {
        "Skill": "ATTACK",
        "Value": 1
      }
    ],
    "Stats": [
      {
        "Type": "ATTACK_RANGE",
        "Value": 120
      },
      {
        "Type": "ATTACK_SPEED",
        "Value": 2
      },
      {
        "Type": "SLASH_ACCURACY",
        "Value": 8
      },
      {
        "Type": "QUICK_DAMAGE",
        "Value": 10
      }
    ]
  },
  {
    "Name": "Bronze Sword",
    "Description": "Basic sword made from Bronze.",
    "Icon": "bronze_sword",
    "Type": "WEAPON_1H",
    "Price": 60,
    "Requirements": [
      {
        "Skill": "ATTACK",
        "Value": 1
      }
    ],
    "Stats": [
      {
        "Type": "ATTACK_RANGE",
        "Value": 120
      },
      {
        "Type": "ATTACK_SPEED",
        "Value": 2
      },
      {
        "Type": "SLASH_ACCURACY",
        "Value": 15
      },
      {
        "Type": "QUICK_DAMAGE",
        "Value": 15
      }
    ],
    "Smithing": {
      "Level": 4,
      "Experience": 90,
      "Duration": "8 seconds",
      "SellCost": "42g",
      "Materials": [
        {
          "Material": "Bronze Bar",
          "Amount": 6
        }
      ]
    }
  },
  {
    "Name": "Iron Sword",
    "Description": "Sturdy sword made from iron.",
    "Icon": "iron_sword",
    "Type": "WEAPON_1H",
    "Price": 150,
    "Requirements": [
      {
        "Skill": "ATTACK",
        "Value": 10
      }
    ],
    "Stats": [
      {
        "Type": "ATTACK_RANGE",
        "Value": 120
      },
      {
        "Type": "ATTACK_SPEED",
        "Value": 2
      },
      {
        "Type": "SLASH_ACCURACY",
        "Value": 30
      },
      {
        "Type": "QUICK_DAMAGE",
        "Value": 25
      }
    ],
    "Smithing": {
      "Level": 14,
      "Experience": 180,
      "Duration": "12 seconds",
      "SellCost": "105g",
      "Materials": [
        {
          "Material": "Iron Bar",
          "Amount": 6
        }
      ]
    }
  },
  {
    "Name": "Steel Sword",
    "Description": "Strong sword made from steel.",
    "Icon": "steel_sword",
    "Type": "WEAPON_1H",
    "Price": 300,
    "Requirements": [
      {
        "Skill": "ATTACK",
        "Value": 20
      }
    ],
    "Stats": [
      {
        "Type": "ATTACK_RANGE",
        "Value": 120
      },
      {
        "Type": "ATTACK_SPEED",
        "Value": 2
      },
      {
        "Type": "SLASH_ACCURACY",
        "Value": 50
      },
      {
        "Type": "QUICK_DAMAGE",
        "Value": 40
      }
    ],
    "Smithing": {
      "Level": 24,
      "Experience": 330,
      "Duration": "16 seconds",
      "SellCost": "210g",
      "Materials": [
        {
          "Material": "Steel Bar",
          "Amount": 6
        }
      ]
    }
  },
  {
    "Name": "Mithril Sword",
    "Description": "Mystical sword made from mythril.",
    "Icon": "mithril_sword",
    "Type": "WEAPON_1H",
    "Price": 1500,
    "Requirements": [
      {
        "Skill": "ATTACK",
        "Value": 30
      }
    ],
    "Stats": [
      {
        "Type": "ATTACK_RANGE",
        "Value": 120
      },
      {
        "Type": "ATTACK_SPEED",
        "Value": 2
      },
      {
        "Type": "SLASH_ACCURACY",
        "Value": 75
      },
      {
        "Type": "QUICK_DAMAGE",
        "Value": 60
      }
    ],
    "Smithing": {
      "Level": 34,
      "Experience": 930,
      "Duration": "20 seconds",
      "SellCost": "1050g",
      "Materials": [
        {
          "Material": "Mithril Bar",
          "Amount": 6
        }
      ]
    }
  },
  {
    "Name": "Skeleton Rapier",
    "Description": "A rapier used by once proud pioneer",
    "Icon": "skeleton_rapier",
    "Type": "WEAPON_1H",
    "Price": 3000,
    "Requirements": [
      {
        "Skill": "ATTACK",
        "Value": 30
      }
    ],
    "Stats": [
      {
        "Type": "ATTACK_RANGE",
        "Value": 120
      },
      {
        "Type": "ATTACK_SPEED",
        "Value": 2
      },
      {
        "Type": "PIECE_ACCURACY",
        "Value": 75
      },
      {
        "Type": "QUICK_DAMAGE",
        "Value": 60
      }
    ]
  },
  {
    "Name": "Goblin Axe",
    "Description": "A make shift goblin axe.",
    "Icon": "goblin_axe",
    "Type": "WEAPON_2H",
    "Price": 1000,
    "Requirements": [
      {
        "Skill": "ATTACK",
        "Value": 5
      }
    ],
    "Stats": [
      {
        "Type": "ATTACK_RANGE",
        "Value": 150
      },
      {
        "Type": "ATTACK_SPEED",
        "Value": 3
      },
      {
        "Type": "SLASH_ACCURACY",
        "Value": 30
      },
      {
        "Type": "HEAVY_DAMAGE",
        "Value": 40
      }
    ]
  },
  {
    "Name": "Bandit Spear",
    "Description": "A powerful spear",
    "Icon": "bandit_spear",
    "Type": "WEAPON_2H",
    "Price": 600,
    "Requirements": [
      {
        "Skill": "ATTACK",
        "Value": 15
      }
    ],
    "Stats": [
      {
        "Type": "ATTACK_RANGE",
        "Value": 150
      },
      {
        "Type": "ATTACK_SPEED",
        "Value": 3
      },
      {
        "Type": "PIECE_ACCURACY",
        "Value": 50
      },
      {
        "Type": "HEAVY_DAMAGE",
        "Value": 60
      }
    ]
  },
  {
    "Name": "Skeleton Greatsword",
    "Description": "A dark and powerful greatsword",
    "Icon": "skeleton_greatsword",
    "Type": "WEAPON_2H",
    "Price": 2500,
    "Requirements": [
      {
        "Skill": "ATTACK",
        "Value": 25
      }
    ],
    "Stats": [
      {
        "Type": "ATTACK_RANGE",
        "Value": 150
      },
      {
        "Type": "ATTACK_SPEED",
        "Value": 3
      },
      {
        "Type": "SLASH_ACCURACY",
        "Value": 70
      },
      {
        "Type": "HEAVY_DAMAGE",
        "Value": 100
      }
    ]
  },
  {
    "Name": "Elven Greatsword",
    "Description": "A powerful elven greatsword.",
    "Icon": "elven_greatsword",
    "Type": "WEAPON_2H",
    "Price": 10000,
    "Requirements": [
      {
        "Skill": "ATTACK",
        "Value": 35
      }
    ],
    "Stats": [
      {
        "Type": "ATTACK_RANGE",
        "Value": 150
      },
      {
        "Type": "ATTACK_SPEED",
        "Value": 3
      },
      {
        "Type": "SLASH_ACCURACY",
        "Value": 100
      },
      {
        "Type": "HEAVY_DAMAGE",
        "Value": 150
      }
    ]
  },
  {
    "Name": "Crude Bow",
    "Description": "Makeshift bow, it still works. Supports up to wooden arrows.",
    "Icon": "crude_bow",
    "Type": "BOW",
    "Requirements": [{ "Skill": "ARCHERY", "Value": 1 }],
    "Price": 5,
    "Stats": [
      { "Type": "ATTACK_RANGE", "Value": 750 },
      { "Type": "ATTACK_SPEED", "Value": 1.5 },
      { "Type": "QUICK_DAMAGE", "Value": 5 }
    ]
  },
  {
    "Name": "Wood Bow",
    "Description": "Basic wooden longbow, its got good range. Supports up to bronze arrows.",
    "Icon": "wood_bow",
    "Type": "BOW",
    "Requirements": [{ "Skill": "ARCHERY", "Value": 1 }],
    "Price": 80,
    "Stats": [
      { "Type": "ATTACK_RANGE", "Value": 1200 },
      { "Type": "ATTACK_SPEED", "Value": 2.5 },
      { "Type": "HEAVY_DAMAGE", "Value": 15 }
    ]
  },
  {
    "Name": "Goblin Bow",
    "Description": "Wooden shortbow made by goblins, easy to fire quickly. Supports up to iron arrows.",
    "Icon": "goblin_bow",
    "Type": "BOW",
    "Price": 100,
    "Requirements": [{ "Skill": "ARCHERY", "Value": 5 }],
    "Stats": [
      { "Type": "ATTACK_RANGE", "Value": 750 },
      { "Type": "ATTACK_SPEED", "Value": 1.5 },
      { "Type": "QUICK_DAMAGE", "Value": 20 }
    ]
  },
  {
    "Name": "Birch Bow",
    "Description": "Improved wooden longbow, its got good range. Supports up to iron arrows.",
    "Icon": "birch_bow",
    "Type": "BOW",
    "Requirements": [{ "Skill": "ARCHERY", "Value": 10 }],
    "Price": 250,
    "Stats": [
      { "Type": "ATTACK_RANGE", "Value": 1200 },
      { "Type": "ATTACK_SPEED", "Value": 2.5 },
      { "Type": "HEAVY_DAMAGE", "Value": 30 }
    ]
  },
  {
    "Name": "Willow Bow",
    "Description": "Decent wooden longbow, its got good range. Supports up to steel arrows.",
    "Icon": "willow_bow",
    "Type": "BOW",
    "Requirements": [{ "Skill": "ARCHERY", "Value": 20 }],
    "Price": 1000,
    "Stats": [
      { "Type": "ATTACK_RANGE", "Value": 1200 },
      { "Type": "ATTACK_SPEED", "Value": 2.5 },
      { "Type": "HEAVY_DAMAGE", "Value": 45 }
    ]
  },
  {
    "Name": "Exotic Bow",
    "Description": "Exotic shortbow from other lands, easy to fire quickly. Supports up to steel arrows.",
    "Icon": "exotic_bow",
    "Type": "BOW",
    "Requirements": [{ "Skill": "ARCHERY", "Value": 15 }],
    "Price": 600,
    "Stats": [
      { "Type": "ATTACK_RANGE", "Value": 750 },
      { "Type": "ATTACK_SPEED", "Value": 1.5 },
      { "Type": "QUICK_DAMAGE", "Value": 30 }
    ]
  }
]